git_semver/__init__.py
git_semver/__main__.py
git_semver/_version.py
git_semver/constants.py
git_semver/main.py
git_semver-0.3.2.dist-info/METADATA
git_semver-0.3.2.dist-info/WHEEL
git_semver-0.3.2.dist-info/entry_points.txt
git_semver-0.3.2.dist-info/top_level.txt
git_semver-0.3.2.dist-info/RECORD
