Metadata-Version: 2.1
Name: git-semver
Version: 0.3.2
Summary: Semantic versions management integrated to git.
Home-page: https://github.com/hartym/git-semver
Author: Romain Dorgueil
Author-email: romain@dorgueil.net
License: Apache License, Version 2.0
Download-URL: https://github.com/hartym/git-semver/archive/0.3.2.tar.gz
Platform: UNKNOWN
Requires-Dist: GitPython (<3.2,>=3.1)
Requires-Dist: semantic-version (<2.7)
Provides-Extra: dev
Requires-Dist: coverage (~=4.5) ; extra == 'dev'
Requires-Dist: isort ; extra == 'dev'
Requires-Dist: pytest (~=4.6) ; extra == 'dev'
Requires-Dist: pytest-cov (~=2.7) ; extra == 'dev'
Requires-Dist: sphinx (~=1.7) ; extra == 'dev'
